linux.py
mt5.py
windows.py
mt5-0.0.3.1.dist-info/LICENSE
mt5-0.0.3.1.dist-info/METADATA
mt5-0.0.3.1.dist-info/WHEEL
mt5-0.0.3.1.dist-info/top_level.txt
mt5-0.0.3.1.dist-info/RECORD
